sspace/__init__.py
sspace/conditionals.py
sspace/convert.py
sspace/parser.py
sspace/space.py
sspace/utils.py
sspace/backends/__init__.py
sspace/backends/cspace.py
sspace/backends/ospace.py
sspace/backends/serializer.py
sspace-0.0.0.dist-info/LICENSE
sspace-0.0.0.dist-info/METADATA
sspace-0.0.0.dist-info/WHEEL
sspace-0.0.0.dist-info/top_level.txt
sspace-0.0.0.dist-info/RECORD
